LICENSE
MANIFEST.in
README.rst
setup.cfg
setup.py
django_rednoise.egg-info/PKG-INFO
django_rednoise.egg-info/SOURCES.txt
django_rednoise.egg-info/dependency_links.txt
django_rednoise.egg-info/pbr.json
django_rednoise.egg-info/requires.txt
django_rednoise.egg-info/top_level.txt
rednoise/__init__.py
rednoise/base.py