Metadata-Version: 1.1
Name: django-rednoise
Version: 1.0.3
Summary: Opinionated Django-specific addon for Whitenoise.
Home-page: https://github.com/ryanmcgrath/django-rednoise/
Author: Ryan McGrath
Author-email: ryan@venodesigns.net
License: MIT
Keywords: django,static,wsgi
Platform: UNKNOWN
Classifier: Development Status :: 5 - Production/Stable
Classifier: Framework :: Django
Classifier: Intended Audience :: Developers
Classifier: License :: OSI Approved :: MIT License
Classifier: Operating System :: OS Independent
Classifier: Programming Language :: Python :: 2.7
Classifier: Programming Language :: Python :: 3.3
Classifier: Programming Language :: Python :: 3.4
